COPYING
MANIFEST.in
README.rst
setup.py
nfsn/__init__.py
nfsn/auth.py
nfsn/nfsnbeanbag.py
nfsn/cli/__init__.py
nfsn/tests/__init__.py
nfsn/tests/test_api.py
nfsn/tests/test_auth.py
nfsn/tests/test_cli.py
nfsn/tests/test_nfsnbeanbag.py
nfsn/tests/fixtures/nfsn-api-credential
nfsn/tests/fixtures/responses/account/A1B2-C3D4E5F6/addSite
nfsn/tests/fixtures/responses/account/A1B2-C3D4E5F6/addWarning
nfsn/tests/fixtures/responses/account/A1B2-C3D4E5F6/balance
nfsn/tests/fixtures/responses/account/A1B2-C3D4E5F6/friendlyName
nfsn/tests/fixtures/responses/account/A1B2-C3D4E5F6/removeWarning
nfsn/tests/fixtures/responses/account/A1B2-C3D4E5F6/sites
nfsn/tests/fixtures/responses/account/A1B2-C3D4E5F6/status
nfsn/tests/fixtures/responses/dns/example.com/addRR
nfsn/tests/fixtures/responses/dns/example.com/expire
nfsn/tests/fixtures/responses/dns/example.com/listRRs
nfsn/tests/fixtures/responses/dns/example.com/minTTL
nfsn/tests/fixtures/responses/dns/example.com/refresh
nfsn/tests/fixtures/responses/dns/example.com/removeRR
nfsn/tests/fixtures/responses/dns/example.com/retry
nfsn/tests/fixtures/responses/dns/example.com/serial
nfsn/tests/fixtures/responses/dns/example.com/updateSerial
nfsn/tests/fixtures/responses/email/example.com/listForwards
nfsn/tests/fixtures/responses/email/example.com/removeForward
nfsn/tests/fixtures/responses/email/example.com/setForward
nfsn/tests/fixtures/responses/member/guest/accounts
nfsn/tests/fixtures/responses/member/guest/sites
nfsn/tests/fixtures/responses/site/mycoolsite/addAlias
nfsn/tests/fixtures/responses/site/mycoolsite/removeAlias
python_nfsn.egg-info/PKG-INFO
python_nfsn.egg-info/SOURCES.txt
python_nfsn.egg-info/dependency_links.txt
python_nfsn.egg-info/entry_points.txt
python_nfsn.egg-info/pbr.json
python_nfsn.egg-info/requires.txt
python_nfsn.egg-info/top_level.txt