Metadata-Version: 1.1
Name: python-nfsn
Version: 1.1.1
Summary: Interact with NearlyFreeSpeech's API
Home-page: https://github.com/ktdreyer/python-nfsn
Author: ken dreyer
Author-email: ktdreyer [at] ktdreyer [dot] com
License: License :: CC0 1.0 Universal (CC0 1.0) Public Domain Dedication
Keywords: nearlyfreespeech.net
Platform: UNKNOWN
Classifier: Development Status :: 4 - Beta
Classifier: License :: CC0 1.0 Universal (CC0 1.0) Public Domain Dedication
Classifier: Operating System :: OS Independent
Classifier: Programming Language :: Python
Classifier: Topic :: Software Development :: Libraries :: Python Modules
